[
  {
    "id": "flower-preservation",
    "name": "Flower Preservation",
    "category": "flower-preservation",
    "parentCategory": "flower-preservation",
    "categoryLabel": "Flower Preservation",
    "description": "Turn bouquets, memorial flowers, or meaningful blooms into timeless keepsakes.",
    "price": "From €89",
    "priceType": "starting",
    "featured": true,
    "available": true,
    "cta": "Request Quote",
    "image": "/assets/images/photo_frame.jpeg",
    "gallery": [
      "/assets/images/photo_frame.jpeg",
      "/assets/images/bookend.png",
      "/assets/images/letter R.jpeg"
    ]
  },
  {
    "id": "bookends",
    "name": "Bookends",
    "category": "bookends",
    "parentCategory": "home-decor",
    "categoryLabel": "Bookends",
    "description": "Elegant floral bookends that hold your stories and memories.",
    "price": "From €149",
    "priceType": "starting",
    "featured": true,
    "available": true,
    "cta": "Request Quote",
    "image": "/assets/images/bookend.png",
    "gallery": [
      "/assets/images/bookend.png",
      "/assets/images/tray.png",
      "/assets/images/letter.png"
    ]
  },
  {
    "id": "letters",
    "name": "Personalized Letters",
    "category": "letters",
    "parentCategory": "personalized-gifts",
    "categoryLabel": "Personalized Letters",
    "description": "Custom initials, names, or words handcrafted to celebrate what matters most.",
    "price": "From €49",
    "priceType": "starting",
    "featured": true,
    "available": true,
    "cta": "Request Quote",
    "image": "/assets/images/letter.png",
    "gallery": [
      "/assets/images/letter.png",
      "/assets/images/bookmark.jpeg",
      "/assets/images/earring.png"
    ]
  },
  {
    "id": "trays",
    "name": "Trays",
    "category": "trays",
    "parentCategory": "home-decor",
    "categoryLabel": "Trays",
    "description": "Personalized decorative trays for serving, jewellery, or display.",
    "price": "From €22",
    "priceType": "starting",
    "featured": true,
    "available": true,
    "cta": "Request Quote",
    "image": "/assets/images/tray 3.jpeg",
    "gallery": [
      "/assets/images/tray 3.jpeg",
      "/assets/images/bookend.png",
      "/assets/images/clock.png"
    ]
  },
  {
    "id": "coasters",
    "name": "Coasters",
    "category": "coasters",
    "parentCategory": "home-decor",
    "categoryLabel": "Coasters",
    "description": "Handcrafted floral coasters that protect surfaces with elegant design.",
    "price": "From €35 per set",
    "priceType": "range",
    "featured": true,
    "available": true,
    "cta": "Request Quote",
    "image": "/assets/images/coasters.png",
    "gallery": [
      "/assets/images/coasters.png",
      "/assets/images/tray 3.jpeg",
      "/assets/images/bookmark.jpeg"
    ]
  },
  {
    "id": "bookmarks-classic",
    "name": "Classic Bookmark",
    "category": "bookmarks",
    "parentCategory": "personalized-gifts",
    "categoryLabel": "Classic Bookmark",
    "description": "Elegant handcrafted bookmark for everyday reading.",
    "price": "From €9",
    "priceType": "starting",
    "featured": true,
    "available": true,
    "cta": "Request Quote",
    "image": "/assets/images/bookmark.jpeg",
    "gallery": [
      "/assets/images/bookmark.jpeg",
      "/assets/images/letter.png",
      "/assets/images/earring.png"
    ]
  },
  {
    "id": "bookmarks-personalized",
    "name": "Personalized Floral Bookmark",
    "category": "bookmarks",
    "parentCategory": "personalized-gifts",
    "categoryLabel": "Personalized Floral Bookmark",
    "description": "Custom bookmark featuring your name and preserved flowers.",
    "price": "From €14",
    "priceType": "starting",
    "featured": true,
    "available": true,
    "cta": "Request Quote",
    "image": "/assets/images/personalised-bookmark.png",
    "gallery": [
      "/assets/images/personalised-bookmark.png",
      "/assets/images/letter.png",
      "/assets/images/earring.png"
    ]
  },
  {
    "id": "earrings",
    "name": "Earrings",
    "category": "earrings",
    "parentCategory": "jewelry",
    "categoryLabel": "Earrings",
    "description": "Lightweight botanical earrings with real preserved flowers.",
    "price": "From €10",
    "priceType": "starting",
    "featured": true,
    "available": true,
    "cta": "Request Quote",
    "image": "/assets/images/earring.png",
    "gallery": [
      "/assets/images/earring.png",
      "/assets/images/bookmark.jpeg",
      "/assets/images/letter.png"
    ]
  },
  {
    "id": "clocks",
    "name": "Clocks",
    "category": "clocks",
    "parentCategory": "home-decor",
    "categoryLabel": "Clocks",
    "description": "Decorative clocks that preserve memories with elegance.",
    "price": "From €99",
    "priceType": "starting",
    "featured": true,
    "available": true,
    "cta": "Request Quote",
    "image": "/assets/images/clock.png",
    "gallery": [
      "/assets/images/clock.png",
      "/assets/images/bookend.png",
      "/assets/images/tray.png"
    ]
  }
]
